pkg/__init__.py
pkg/models.py
irismodel-0.0.10.dist-info/METADATA
irismodel-0.0.10.dist-info/WHEEL
irismodel-0.0.10.dist-info/top_level.txt
irismodel-0.0.10.dist-info/RECORD
