Metadata-Version: 2.1
Name: irismodel
Version: 0.0.10
Summary: Slim Iris Model
Home-page: UNKNOWN
Author: Lars Kjeldgaard
Author-email: lars_kjeldgaard@hotmail.com
License: UNKNOWN
Platform: UNKNOWN
Classifier: Programming Language :: Python :: 3
Classifier: License :: OSI Approved :: MIT License
Classifier: Operating System :: OS Independent
Requires-Python: >=3.6
Requires-Dist: sklearn
Requires-Dist: numpy
